regi/__init__.py
regi/rigi.py
rege-1.0.dist-info/LICENCE.txt
rege-1.0.dist-info/METADATA
rege-1.0.dist-info/WHEEL
rege-1.0.dist-info/top_level.txt
rege-1.0.dist-info/RECORD
