Metadata-Version: 2.1
Name: rege
Version: 1.0
Summary: Different Types of Regression
Author: Sahraoui Tarek Ziad
Author-email: tziad2027@gmail.com
License-File: LICENCE.txt
